LICENSE
LICENSE.txt
README.md
setup.cfg
setup.py
hsemotion/__init__.py
hsemotion/facial_emotions.py
hsemotion.egg-info/PKG-INFO
hsemotion.egg-info/SOURCES.txt
hsemotion.egg-info/dependency_links.txt
hsemotion.egg-info/requires.txt
hsemotion.egg-info/top_level.txt