Metadata-Version: 1.1
Name: hsemotion
Version: 0.3.0
Summary: HSEmotion Python Library for Facial Emotion Recognition
Home-page: https://github.com/HSE-asavchenko/face-emotion-recognition
Author: Andrey Savchenko
Author-email: andrey.v.savchenko@gmail.com
License: Apache-2.0
Download-URL: https://github.com/HSE-asavchenko/hsemotion/archive/v0.3.0.tar.gz
Keywords: face expression recognition,emotion analysis,facial expressions
Platform: UNKNOWN
